croquis/__init__.py
croquis/axis_util.py
croquis/buf_util.py
croquis/color_util.py
croquis/comm.py
croquis/data_util.py
croquis/datatype_util.py
croquis/display.py
croquis/env_helper.py
croquis/fig_data.py
croquis/log_util.py
croquis/misc_util.py
croquis/plot.py
croquis/png_util.py
croquis/thr_manager.py
croquis/lib/_csrc.cpython-312-x86_64-linux-gnu.so
croquis/tests/axis_util_test.py
croquis/tests/data_util_test.py
croquis-0.2.0.data/data/share/jupyter/labextensions/croquis-js/package.json
croquis-0.2.0.data/data/share/jupyter/labextensions/croquis-js/static/604.99f0ee3c82f0cb531e72.js
croquis-0.2.0.data/data/share/jupyter/labextensions/croquis-js/static/677.257947746a08a546077c.js
croquis-0.2.0.data/data/share/jupyter/labextensions/croquis-js/static/remoteEntry.906705496ffc13dbdc8f.js
croquis-0.2.0.data/data/share/jupyter/labextensions/croquis-js/static/style.js
croquis-0.2.0.data/data/share/jupyter/labextensions/croquis-js/static/third-party-licenses.json
croquis-0.2.0.dist-info/METADATA
croquis-0.2.0.dist-info/WHEEL
croquis-0.2.0.dist-info/RECORD
croquis-0.2.0.dist-info/licenses/LICENSE
