Metadata-Version: 2.4
Name: croquis
Version: 0.2.0
Summary: Library for plotting interactive graphs on Jupyter Notebook
Project-URL: Homepage, https://github.com/yongjik/croquis
Author-email: Yongjik Kim <yongjik@gmail.com>
License-Expression: MIT
License-File: LICENSE
Classifier: Framework :: Jupyter
Classifier: Framework :: Jupyter :: JupyterLab
Classifier: Framework :: Jupyter :: JupyterLab :: Extensions
Classifier: Operating System :: POSIX :: Linux
Classifier: Programming Language :: Python :: 3
Classifier: Programming Language :: Python :: Implementation :: CPython
Requires-Python: >=3.9
Requires-Dist: numpy>=1.15.0
